gztarchiver/main.py
gztarchiver/doc_inspector/LLM/__init__.py
gztarchiver/doc_inspector/LLM/prompt_templates.py
gztarchiver/doc_inspector/utils/__init__.py
gztarchiver/doc_inspector/utils/categorizing_utils.py
gztarchiver/doc_inspector/utils/content_preprocessing_utils.py
gztarchiver/doc_scraper/cmd/__init__.py
gztarchiver/doc_scraper/cmd/parser.py
gztarchiver/doc_scraper/cmd/validator.py
gztarchiver/doc_scraper/crawler/__init__.py
gztarchiver/doc_scraper/crawler/run_crawlers.py
gztarchiver/doc_scraper/utils/__init__.py
gztarchiver/doc_scraper/utils/archive_folder_utils.py
gztarchiver/doc_scraper/utils/archive_to_cloud_utils.py
gztarchiver/doc_scraper/utils/cloud_credential_utils.py
gztarchiver/doc_scraper/utils/db_utils.py
gztarchiver/doc_scraper/utils/doc_metadata_utils.py
gztarchiver/doc_scraper/utils/hide_logs_utils.py
gztarchiver/doc_scraper/utils/year_data_utils.py
gztarchiver/document_scraper/document_scraper/__init__.py
gztarchiver/document_scraper/document_scraper/items.py
gztarchiver/document_scraper/document_scraper/middlewares.py
gztarchiver/document_scraper/document_scraper/pipelines.py
gztarchiver/document_scraper/document_scraper/settings.py
gztarchiver/document_scraper/document_scraper/spiders/__init__.py
gztarchiver/document_scraper/document_scraper/spiders/doc_download_spider.py
gztarchiver/document_scraper/document_scraper/spiders/doc_metadata_spider.py
gztarchiver/document_scraper/document_scraper/spiders/years_spider.py
gztarchiver-0.1.0.dist-info/METADATA
gztarchiver-0.1.0.dist-info/WHEEL
gztarchiver-0.1.0.dist-info/entry_points.txt
gztarchiver-0.1.0.dist-info/top_level.txt
gztarchiver-0.1.0.dist-info/RECORD
